MANIFEST.in
README.md
setup.py
bin/qscan
qscan/__init__.py
qscan/commands.py
qscan/fortio.py
qscan/main.py
qscan/plots.py
qscan/retrieve.py
qscan/settings.py
qscan/voigt.py
qscan.egg-info/PKG-INFO
qscan.egg-info/SOURCES.txt
qscan.egg-info/dependency_links.txt
qscan.egg-info/requires.txt
qscan.egg-info/top_level.txt
qscan/data/atmolines.dat
qscan/data/atom.dat
qscan/data/hydrolist.dat
qscan/data/metallist.dat