Metadata-Version: 2.1
Name: qscan
Version: 2.5.3
Summary: Quasar spectrum scanner and first guess Voigt profile modelling software.
Home-page: https://astroquasar.gitlab.io/qscan/
Author: Vincent Dumont
Author-email: vincentdumont@gmail.com
License: UNKNOWN
Project-URL: Source Code, https://gitlab.com/astroquasar/programs/qscan
Platform: UNKNOWN
